{
  "recipeTitle": "S'Mauros: Skillet S'Mores",
  "ingredients": [
    "3 tablespoons unsalted butter",
    "1 cup walnuts, roughly chopped",
    "One 12-ounce bag mini chocolate chips",
    "3 cups mini marshmallows",
    "Graham crackers, broken into squares, for dipping"
  ],
  "directions": [
    "Preheat the broiler on high.",
    "Heat a cast-iron skillet over medium heat. Melt the butter in the skillet, add the nuts and toast until fragrant. Remove from the heat and sprinkle the chocolate chips evenly over the nuts. Spread the marshmallows over the chocolate chips. Place the skillet under the broiler until browned on top.",
    "Serve in the skillet and use graham cracker squares for dipping."
  ],
  "recipeImage": "http://foodnetwork.sndimg.com/content/dam/images/food/fullset/2014/4/18/1/KC0202_Smores-Skillet_s4x3.jpg.rend.sni12col.landscape.jpeg",
  "recipeURL": "http://www.foodnetwork.com/recipes/jeff-mauro/smauros-skillet-smores.html"
}
